Workbook

Sheet Contributions
A1: Onyx Accounting Group, LLC - Angle Health + Questco
A2: Medical placed with Angle Health through CapFi. All other PEO services through Questco. Medical effective 10/01/2026.
A3: EDIT THE YELLOW CELLS ONLY. Every other number on every tab recalculates from them.
A5: 1. ONYX MONTHLY CONTRIBUTION BY TIER <- this is the lever
A6: Tier | B6: Code | C6: Onyx pays $/mo | D6: Onyx pays $/yr | E6: Angle minimum funding $/mo | F6: Clears the minimum?
A7: Employee only | B7: EE | C7: 300 | D7: =C7*12 -> 3600 | E7: =$C$16 -> 219.515 | F7: =IF(C7>=E7,"Yes","NO - below Angle minimum") -> Yes
A8: Employee + spouse | B8: ES | C8: 600 | D8: =C8*12 -> 7200 | E8: =$C$16 -> 219.515 | F8: =IF(C8>=E8,"Yes","NO - below Angle minimum") -> Yes
A9: Employee + child(ren) | B9: EC | C9: 600 | D9: =C9*12 -> 7200 | E9: =$C$16 -> 219.515 | F9: =IF(C9>=E9,"Yes","NO - below Angle minimum") -> Yes
A10: Family | B10: FAM | C10: 1000 | D10: =C10*12 -> 12000 | E10: =$C$16 -> 219.515 | F10: =IF(C10>=E10,"Yes","NO - below Angle minimum") -> Yes
A12: Fixed dollars, medical only. Dental and vision are not offered by Angle; life, LTD and STD are quoted separately by Questco on the Questco tab.
A14: 2. ANGLE MINIMUM FUNDING REQUIREMENT
A15: Percentage of the lowest employee-only rate | C15: 0.5
A16: Minimum Onyx must fund, per enrolled employee, per month | C16: =C15*MIN('Angle Plans'!L5:L7) -> 219.515
A17: Minimum total funding at current enrollment, per year | C17: =C16*C34*12 -> 10536.72
A18: Angle's own presentation states minimum funding of $10,536.96/yr - 50% of the HDHP 3400/5000's $439.03 employee-only rate across four enrolled employees. The formula above lands at $10,536.72; the 24-cent difference is Angle rounding the monthly floor to $219.52.
A20: 3. WHO IS ENROLLED <- change Yes/No to re-run the whole model
A21: Employee | B21: Annual pay | C21: Medical tier | D21: Code | E21: Enrolling? | F21: Note
A22: Steven Nikolov | B22: 186000 | C22: Family | D22: FAM | E22: Yes | F22: 100% owner. >2% S-corp shareholder - premiums cannot run pretax through the cafeteria plan (IRC 1372).
A23: Lisa Danforth | B23: 178094 | C23: Employee only | D23: EE | E23: Yes
A24: Jessica Bumphus | B24: 135000 | C24: Family | D24: FAM | E24: Yes | F24: New hire.
A25: Christine Johnson | B25: 79228 | C25: Employee + spouse | D25: ES | E25: Yes | F25: Lowest salary, second-highest tier - feels the deduction hardest.
A26: Josephine Mack | B26: 80000 | C26: Family | D26: FAM | E26: No | F26: Waiving. Shown so the model can be re-run with her enrolled - change to Yes.
A28: 4. ENROLLMENT AND COST AT THE CURRENT SETTINGS
A29: Tier | B29: Code | C29: Enrolled | D29: Onyx $/mo | E29: Onyx $/yr
A30: Employee only | B30: EE | C30: =COUNTIFS($D$22:$D$26,B30,$E$22:$E$26,"Yes") -> 1 | D30: =C30*INDEX($C$7:$C$10,MATCH(B30,$B$7:$B$10,0)) -> 300 | E30: =D30*12 -> 3600
A31: Employee + spouse | B31: ES | C31: =COUNTIFS($D$22:$D$26,B31,$E$22:$E$26,"Yes") -> 1 | D31: =C31*INDEX($C$7:$C$10,MATCH(B31,$B$7:$B$10,0)) -> 600 | E31: =D31*12 -> 7200
A32: Employee + child(ren) | B32: EC | C32: =COUNTIFS($D$22:$D$26,B32,$E$22:$E$26,"Yes") -> 0 | D32: =C32*INDEX($C$7:$C$10,MATCH(B32,$B$7:$B$10,0)) -> 0 | E32: =D32*12 -> 0
A33: Family | B33: FAM | C33: =COUNTIFS($D$22:$D$26,B33,$E$22:$E$26,"Yes") -> 2 | D33: =C33*INDEX($C$7:$C$10,MATCH(B33,$B$7:$B$10,0)) -> 2000 | E33: =D33*12 -> 24000
A34: TOTAL | C34: =SUM(C30:C33) -> 4 | D34: =SUM(D30:D33) -> 2900 | E34: =SUM(E30:E33) -> 34800

Sheet Angle Plans
A1: Angle Health - all three plans
A2: Level funded on the Cigna PPO network. Out-of-network is covered at 50% after a separate out-of-network deductible. Coinsurance is the share the PLAN pays after the deductible.
A4: Plan | B4: HSA | C4: Ded individual | D4: Ded family | E4: OOP max individual | F4: OOP max family | G4: Coins (plan pays) | H4: PCP | I4: Specialist | J4: Rx | K4: Emergency room | L4: EE | M4: ES | N4: EC | O4: FAM | P4: Note
A5: ANG HDHP 3400/5000 | B5: Y | C5: 3400 | D5: 6800 | E5: 5000 | F5: 10000 | G5: 0.8 | H5: 20% after ded | I5: 20% after ded | J5: 20% after ded (all tiers) | K5: 20% after ded | L5: 439.03 | M5: 921.97 | N5: 834.16 | O5: 1361 | P5: CapFi's recommended base plan. Sets the minimum-funding floor.
A6: ANG TRAD 2000/4000 | B6: N | C6: 2000 | D6: 4000 | E6: 4000 | F6: 8000 | G6: 0.8 | H6: $20 | I6: $50 | J6: $20 / $60 | K6: $250 | L6: 492.11 | M6: 1033.43 | N6: 934.01 | O6: 1525.54 | P6: Tier rates DERIVED from the ratios in the two documented plans. Confirm with CapFi before quoting to employees.
A7: ANG TRAD 1000/2000 | B7: N | C7: 1000 | D7: 2000 | E7: 2000 | F7: 4000 | G7: 0.8 | H7: $10 | I7: $30 | J7: $10 / $30 | K7: $200 | L7: 546.33 | M7: 1147.29 | N7: 1038.02 | O7: 1693.61 | P7: Best plan design in the whole field - $1,000 deductible, $2,000 out-of-pocket maximum.
A9: Every cell above is transcribed from the CapFi / Angle Health presentation, quote 400798, underwritten 7/30/2026.

Sheet Cost by Tier
A1: What each Angle plan costs Onyx and the employee
A2: Onyx pays the greater of its tier contribution and Angle's minimum funding, never more than the premium. Worst case = the employee's annual premium plus that household's in-network out-of-pocket maximum; premiums never count toward an out-of-pocket maximum, so the two add without overlapping.
A4: Plan | B4: Tier | C4: Code | D4: Enrolled | E4: Monthly premium | F4: Onyx contribution $/mo | G4: Angle minimum $/mo | H4: Onyx pays $/mo | I4: Employee pays $/mo | J4: Onyx share | K4: Onyx $/yr (all enrolled) | L4: Employee $/yr (each) | M4: Deductible | N4: OOP max | O4: Worst case $/yr (each) | P4: Employee $/yr (all in tier) | Q4: Row key
A5: ANG HDHP 3400/5000 | B5: Employee only | C5: EE | D5: =COUNTIFS(Contributions!$D$22:$D$26,$C5,Contributions!$E$22:$E$26,"Yes") -> 1 | E5: =INDEX('Angle Plans'!$L$5:$O$7,MATCH($A5,'Angle Plans'!$A$5:$A$7,0),MATCH($C5,'Angle Plans'!$L$4:$O$4,0)) -> 439.03 | F5: =INDEX(Contributions!$C$7:$C$10,MATCH($C5,Contributions!$B$7:$B$10,0)) -> 300 | G5: =Contributions!$C$16 -> 219.515 | H5: =MIN($E5,MAX($F5,$G5)) -> 300 | I5: =$E5-$H5 -> 139.03 | J5: =IF($E5=0,0,$H5/$E5) -> 0.6833246 | K5: =$H5*$D5*12 -> 3600 | L5: =$I5*12 -> 1668.36 | M5: =IF($C5="EE",INDEX('Angle Plans'!$C$5:$C$7,MATCH($A5,'Angle Plans'!$A$5:$A$7,0)),INDEX('Angle Plans'!$D$5:$D$7,MATCH($A5,'Angle Plans'!$A$5:$A$7,0))) -> 3400 | N5: =IF($C5="EE",INDEX('Angle Plans'!$E$5:$E$7,MATCH($A5,'Angle Plans'!$A$5:$A$7,0)),INDEX('Angle Plans'!$F$5:$F$7,MATCH($A5,'Angle Plans'!$A$5:$A$7,0))) -> 5000 | O5: =$L5+$N5 -> 6668.36 | P5: =$I5*$D5*12 -> 1668.36 | Q5: =$A5&"|"&$C5 -> ANG HDHP 3400/5000|EE
A6: ANG HDHP 3400/5000 | B6: Employee + spouse | C6: ES | D6: =COUNTIFS(Contributions!$D$22:$D$26,$C6,Contributions!$E$22:$E$26,"Yes") -> 1 | E6: =INDEX('Angle Plans'!$L$5:$O$7,MATCH($A6,'Angle Plans'!$A$5:$A$7,0),MATCH($C6,'Angle Plans'!$L$4:$O$4,0)) -> 921.97 | F6: =INDEX(Contributions!$C$7:$C$10,MATCH($C6,Contributions!$B$7:$B$10,0)) -> 600 | G6: =Contributions!$C$16 -> 219.515 | H6: =MIN($E6,MAX($F6,$G6)) -> 600 | I6: =$E6-$H6 -> 321.97 | J6: =IF($E6=0,0,$H6/$E6) -> 0.65078039 | K6: =$H6*$D6*12 -> 7200 | L6: =$I6*12 -> 3863.64 | M6: =IF($C6="EE",INDEX('Angle Plans'!$C$5:$C$7,MATCH($A6,'Angle Plans'!$A$5:$A$7,0)),INDEX('Angle Plans'!$D$5:$D$7,MATCH($A6,'Angle Plans'!$A$5:$A$7,0))) -> 6800 | N6: =IF($C6="EE",INDEX('Angle Plans'!$E$5:$E$7,MATCH($A6,'Angle Plans'!$A$5:$A$7,0)),INDEX('Angle Plans'!$F$5:$F$7,MATCH($A6,'Angle Plans'!$A$5:$A$7,0))) -> 10000 | O6: =$L6+$N6 -> 13863.64 | P6: =$I6*$D6*12 -> 3863.64 | Q6: =$A6&"|"&$C6 -> ANG HDHP 3400/5000|ES
A7: ANG HDHP 3400/5000 | B7: Employee + child(ren) | C7: EC | D7: =COUNTIFS(Contributions!$D$22:$D$26,$C7,Contributions!$E$22:$E$26,"Yes") -> 0 | E7: =INDEX('Angle Plans'!$L$5:$O$7,MATCH($A7,'Angle Plans'!$A$5:$A$7,0),MATCH($C7,'Angle Plans'!$L$4:$O$4,0)) -> 834.16 | F7: =INDEX(Contributions!$C$7:$C$10,MATCH($C7,Contributions!$B$7:$B$10,0)) -> 600 | G7: =Contributions!$C$16 -> 219.515 | H7: =MIN($E7,MAX($F7,$G7)) -> 600 | I7: =$E7-$H7 -> 234.16 | J7: =IF($E7=0,0,$H7/$E7) -> 0.71928647 | K7: =$H7*$D7*12 -> 0 | L7: =$I7*12 -> 2809.92 | M7: =IF($C7="EE",INDEX('Angle Plans'!$C$5:$C$7,MATCH($A7,'Angle Plans'!$A$5:$A$7,0)),INDEX('Angle Plans'!$D$5:$D$7,MATCH($A7,'Angle Plans'!$A$5:$A$7,0))) -> 6800 | N7: =IF($C7="EE",INDEX('Angle Plans'!$E$5:$E$7,MATCH($A7,'Angle Plans'!$A$5:$A$7,0)),INDEX('Angle Plans'!$F$5:$F$7,MATCH($A7,'Angle Plans'!$A$5:$A$7,0))) -> 10000 | O7: =$L7+$N7 -> 12809.92 | P7: =$I7*$D7*12 -> 0 | Q7: =$A7&"|"&$C7 -> ANG HDHP 3400/5000|EC
A8: ANG HDHP 3400/5000 | B8: Family | C8: FAM | D8: =COUNTIFS(Contributions!$D$22:$D$26,$C8,Contributions!$E$22:$E$26,"Yes") -> 2 | E8: =INDEX('Angle Plans'!$L$5:$O$7,MATCH($A8,'Angle Plans'!$A$5:$A$7,0),MATCH($C8,'Angle Plans'!$L$4:$O$4,0)) -> 1361 | F8: =INDEX(Contributions!$C$7:$C$10,MATCH($C8,Contributions!$B$7:$B$10,0)) -> 1000 | G8: =Contributions!$C$16 -> 219.515 | H8: =MIN($E8,MAX($F8,$G8)) -> 1000 | I8: =$E8-$H8 -> 361 | J8: =IF($E8=0,0,$H8/$E8) -> 0.73475386 | K8: =$H8*$D8*12 -> 24000 | L8: =$I8*12 -> 4332 | M8: =IF($C8="EE",INDEX('Angle Plans'!$C$5:$C$7,MATCH($A8,'Angle Plans'!$A$5:$A$7,0)),INDEX('Angle Plans'!$D$5:$D$7,MATCH($A8,'Angle Plans'!$A$5:$A$7,0))) -> 6800 | N8: =IF($C8="EE",INDEX('Angle Plans'!$E$5:$E$7,MATCH($A8,'Angle Plans'!$A$5:$A$7,0)),INDEX('Angle Plans'!$F$5:$F$7,MATCH($A8,'Angle Plans'!$A$5:$A$7,0))) -> 10000 | O8: =$L8+$N8 -> 14332 | P8: =$I8*$D8*12 -> 8664 | Q8: =$A8&"|"&$C8 -> ANG HDHP 3400/5000|FAM
A9: ANG TRAD 2000/4000 | B9: Employee only | C9: EE | D9: =COUNTIFS(Contributions!$D$22:$D$26,$C9,Contributions!$E$22:$E$26,"Yes") -> 1 | E9: =INDEX('Angle Plans'!$L$5:$O$7,MATCH($A9,'Angle Plans'!$A$5:$A$7,0),MATCH($C9,'Angle Plans'!$L$4:$O$4,0)) -> 492.11 | F9: =INDEX(Contributions!$C$7:$C$10,MATCH($C9,Contributions!$B$7:$B$10,0)) -> 300 | G9: =Contributions!$C$16 -> 219.515 | H9: =MIN($E9,MAX($F9,$G9)) -> 300 | I9: =$E9-$H9 -> 192.11 | J9: =IF($E9=0,0,$H9/$E9) -> 0.6096198 | K9: =$H9*$D9*12 -> 3600 | L9: =$I9*12 -> 2305.32 | M9: =IF($C9="EE",INDEX('Angle Plans'!$C$5:$C$7,MATCH($A9,'Angle Plans'!$A$5:$A$7,0)),INDEX('Angle Plans'!$D$5:$D$7,MATCH($A9,'Angle Plans'!$A$5:$A$7,0))) -> 2000 | N9: =IF($C9="EE",INDEX('Angle Plans'!$E$5:$E$7,MATCH($A9,'Angle Plans'!$A$5:$A$7,0)),INDEX('Angle Plans'!$F$5:$F$7,MATCH($A9,'Angle Plans'!$A$5:$A$7,0))) -> 4000 | O9: =$L9+$N9 -> 6305.32 | P9: =$I9*$D9*12 -> 2305.32 | Q9: =$A9&"|"&$C9 -> ANG TRAD 2000/4000|EE
A10: ANG TRAD 2000/4000 | B10: Employee + spouse | C10: ES | D10: =COUNTIFS(Contributions!$D$22:$D$26,$C10,Contributions!$E$22:$E$26,"Yes") -> 1 | E10: =INDEX('Angle Plans'!$L$5:$O$7,MATCH($A10,'Angle Plans'!$A$5:$A$7,0),MATCH($C10,'Angle Plans'!$L$4:$O$4,0)) -> 1033.43 | F10: =INDEX(Contributions!$C$7:$C$10,MATCH($C10,Contributions!$B$7:$B$10,0)) -> 600 | G10: =Contributions!$C$16 -> 219.515 | H10: =MIN($E10,MAX($F10,$G10)) -> 600 | I10: =$E10-$H10 -> 433.43 | J10: =IF($E10=0,0,$H10/$E10) -> 0.58059085 | K10: =$H10*$D10*12 -> 7200 | L10: =$I10*12 -> 5201.16 | M10: =IF($C10="EE",INDEX('Angle Plans'!$C$5:$C$7,MATCH($A10,'Angle Plans'!$A$5:$A$7,0)),INDEX('Angle Plans'!$D$5:$D$7,MATCH($A10,'Angle Plans'!$A$5:$A$7,0))) -> 4000 | N10: =IF($C10="EE",INDEX('Angle Plans'!$E$5:$E$7,MATCH($A10,'Angle Plans'!$A$5:$A$7,0)),INDEX('Angle Plans'!$F$5:$F$7,MATCH($A10,'Angle Plans'!$A$5:$A$7,0))) -> 8000 | O10: =$L10+$N10 -> 13201.16 | P10: =$I10*$D10*12 -> 5201.16 | Q10: =$A10&"|"&$C10 -> ANG TRAD 2000/4000|ES
A11: ANG TRAD 2000/4000 | B11: Employee + child(ren) | C11: EC | D11: =COUNTIFS(Contributions!$D$22:$D$26,$C11,Contributions!$E$22:$E$26,"Yes") -> 0 | E11: =INDEX('Angle Plans'!$L$5:$O$7,MATCH($A11,'Angle Plans'!$A$5:$A$7,0),MATCH($C11,'Angle Plans'!$L$4:$O$4,0)) -> 934.01 | F11: =INDEX(Contributions!$C$7:$C$10,MATCH($C11,Contributions!$B$7:$B$10,0)) -> 600 | G11: =Contributions!$C$16 -> 219.515 | H11: =MIN($E11,MAX($F11,$G11)) -> 600 | I11: =$E11-$H11 -> 334.01 | J11: =IF($E11=0,0,$H11/$E11) -> 0.64239141 | K11: =$H11*$D11*12 -> 0 | L11: =$I11*12 -> 4008.12 | M11: =IF($C11="EE",INDEX('Angle Plans'!$C$5:$C$7,MATCH($A11,'Angle Plans'!$A$5:$A$7,0)),INDEX('Angle Plans'!$D$5:$D$7,MATCH($A11,'Angle Plans'!$A$5:$A$7,0))) -> 4000 | N11: =IF($C11="EE",INDEX('Angle Plans'!$E$5:$E$7,MATCH($A11,'Angle Plans'!$A$5:$A$7,0)),INDEX('Angle Plans'!$F$5:$F$7,MATCH($A11,'Angle Plans'!$A$5:$A$7,0))) -> 8000 | O11: =$L11+$N11 -> 12008.12 | P11: =$I11*$D11*12 -> 0 | Q11: =$A11&"|"&$C11 -> ANG TRAD 2000/4000|EC
A12: ANG TRAD 2000/4000 | B12: Family | C12: FAM | D12: =COUNTIFS(Contributions!$D$22:$D$26,$C12,Contributions!$E$22:$E$26,"Yes") -> 2 | E12: =INDEX('Angle Plans'!$L$5:$O$7,MATCH($A12,'Angle Plans'!$A$5:$A$7,0),MATCH($C12,'Angle Plans'!$L$4:$O$4,0)) -> 1525.54 | F12: =INDEX(Contributions!$C$7:$C$10,MATCH($C12,Contributions!$B$7:$B$10,0)) -> 1000 | G12: =Contributions!$C$16 -> 219.515 | H12: =MIN($E12,MAX($F12,$G12)) -> 1000 | I12: =$E12-$H12 -> 525.54 | J12: =IF($E12=0,0,$H12/$E12) -> 0.65550559 | K12: =$H12*$D12*12 -> 24000 | L12: =$I12*12 -> 6306.48 | M12: =IF($C12="EE",INDEX('Angle Plans'!$C$5:$C$7,MATCH($A12,'Angle Plans'!$A$5:$A$7,0)),INDEX('Angle Plans'!$D$5:$D$7,MATCH($A12,'Angle Plans'!$A$5:$A$7,0))) -> 4000 | N12: =IF($C12="EE",INDEX('Angle Plans'!$E$5:$E$7,MATCH($A12,'Angle Plans'!$A$5:$A$7,0)),INDEX('Angle Plans'!$F$5:$F$7,MATCH($A12,'Angle Plans'!$A$5:$A$7,0))) -> 8000 | O12: =$L12+$N12 -> 14306.48 | P12: =$I12*$D12*12 -> 12612.96 | Q12: =$A12&"|"&$C12 -> ANG TRAD 2000/4000|FAM
A13: ANG TRAD 1000/2000 | B13: Employee only | C13: EE | D13: =COUNTIFS(Contributions!$D$22:$D$26,$C13,Contributions!$E$22:$E$26,"Yes") -> 1 | E13: =INDEX('Angle Plans'!$L$5:$O$7,MATCH($A13,'Angle Plans'!$A$5:$A$7,0),MATCH($C13,'Angle Plans'!$L$4:$O$4,0)) -> 546.33 | F13: =INDEX(Contributions!$C$7:$C$10,MATCH($C13,Contributions!$B$7:$B$10,0)) -> 300 | G13: =Contributions!$C$16 -> 219.515 | H13: =MIN($E13,MAX($F13,$G13)) -> 300 | I13: =$E13-$H13 -> 246.33 | J13: =IF($E13=0,0,$H13/$E13) -> 0.54911866 | K13: =$H13*$D13*12 -> 3600 | L13: =$I13*12 -> 2955.96 | M13: =IF($C13="EE",INDEX('Angle Plans'!$C$5:$C$7,MATCH($A13,'Angle Plans'!$A$5:$A$7,0)),INDEX('Angle Plans'!$D$5:$D$7,MATCH($A13,'Angle Plans'!$A$5:$A$7,0))) -> 1000 | N13: =IF($C13="EE",INDEX('Angle Plans'!$E$5:$E$7,MATCH($A13,'Angle Plans'!$A$5:$A$7,0)),INDEX('Angle Plans'!$F$5:$F$7,MATCH($A13,'Angle Plans'!$A$5:$A$7,0))) -> 2000 | O13: =$L13+$N13 -> 4955.96 | P13: =$I13*$D13*12 -> 2955.96 | Q13: =$A13&"|"&$C13 -> ANG TRAD 1000/2000|EE
A14: ANG TRAD 1000/2000 | B14: Employee + spouse | C14: ES | D14: =COUNTIFS(Contributions!$D$22:$D$26,$C14,Contributions!$E$22:$E$26,"Yes") -> 1 | E14: =INDEX('Angle Plans'!$L$5:$O$7,MATCH($A14,'Angle Plans'!$A$5:$A$7,0),MATCH($C14,'Angle Plans'!$L$4:$O$4,0)) -> 1147.29 | F14: =INDEX(Contributions!$C$7:$C$10,MATCH($C14,Contributions!$B$7:$B$10,0)) -> 600 | G14: =Contributions!$C$16 -> 219.515 | H14: =MIN($E14,MAX($F14,$G14)) -> 600 | I14: =$E14-$H14 -> 547.29 | J14: =IF($E14=0,0,$H14/$E14) -> 0.52297152 | K14: =$H14*$D14*12 -> 7200 | L14: =$I14*12 -> 6567.48 | M14: =IF($C14="EE",INDEX('Angle Plans'!$C$5:$C$7,MATCH($A14,'Angle Plans'!$A$5:$A$7,0)),INDEX('Angle Plans'!$D$5:$D$7,MATCH($A14,'Angle Plans'!$A$5:$A$7,0))) -> 2000 | N14: =IF($C14="EE",INDEX('Angle Plans'!$E$5:$E$7,MATCH($A14,'Angle Plans'!$A$5:$A$7,0)),INDEX('Angle Plans'!$F$5:$F$7,MATCH($A14,'Angle Plans'!$A$5:$A$7,0))) -> 4000 | O14: =$L14+$N14 -> 10567.48 | P14: =$I14*$D14*12 -> 6567.48 | Q14: =$A14&"|"&$C14 -> ANG TRAD 1000/2000|ES
A15: ANG TRAD 1000/2000 | B15: Employee + child(ren) | C15: EC | D15: =COUNTIFS(Contributions!$D$22:$D$26,$C15,Contributions!$E$22:$E$26,"Yes") -> 0 | E15: =INDEX('Angle Plans'!$L$5:$O$7,MATCH($A15,'Angle Plans'!$A$5:$A$7,0),MATCH($C15,'Angle Plans'!$L$4:$O$4,0)) -> 1038.02 | F15: =INDEX(Contributions!$C$7:$C$10,MATCH($C15,Contributions!$B$7:$B$10,0)) -> 600 | G15: =Contributions!$C$16 -> 219.515 | H15: =MIN($E15,MAX($F15,$G15)) -> 600 | I15: =$E15-$H15 -> 438.02 | J15: =IF($E15=0,0,$H15/$E15) -> 0.57802354 | K15: =$H15*$D15*12 -> 0 | L15: =$I15*12 -> 5256.24 | M15: =IF($C15="EE",INDEX('Angle Plans'!$C$5:$C$7,MATCH($A15,'Angle Plans'!$A$5:$A$7,0)),INDEX('Angle Plans'!$D$5:$D$7,MATCH($A15,'Angle Plans'!$A$5:$A$7,0))) -> 2000 | N15: =IF($C15="EE",INDEX('Angle Plans'!$E$5:$E$7,MATCH($A15,'Angle Plans'!$A$5:$A$7,0)),INDEX('Angle Plans'!$F$5:$F$7,MATCH($A15,'Angle Plans'!$A$5:$A$7,0))) -> 4000 | O15: =$L15+$N15 -> 9256.24 | P15: =$I15*$D15*12 -> 0 | Q15: =$A15&"|"&$C15 -> ANG TRAD 1000/2000|EC
A16: ANG TRAD 1000/2000 | B16: Family | C16: FAM | D16: =COUNTIFS(Contributions!$D$22:$D$26,$C16,Contributions!$E$22:$E$26,"Yes") -> 2 | E16: =INDEX('Angle Plans'!$L$5:$O$7,MATCH($A16,'Angle Plans'!$A$5:$A$7,0),MATCH($C16,'Angle Plans'!$L$4:$O$4,0)) -> 1693.61 | F16: =INDEX(Contributions!$C$7:$C$10,MATCH($C16,Contributions!$B$7:$B$10,0)) -> 1000 | G16: =Contributions!$C$16 -> 219.515 | H16: =MIN($E16,MAX($F16,$G16)) -> 1000 | I16: =$E16-$H16 -> 693.61 | J16: =IF($E16=0,0,$H16/$E16) -> 0.59045471 | K16: =$H16*$D16*12 -> 24000 | L16: =$I16*12 -> 8323.32 | M16: =IF($C16="EE",INDEX('Angle Plans'!$C$5:$C$7,MATCH($A16,'Angle Plans'!$A$5:$A$7,0)),INDEX('Angle Plans'!$D$5:$D$7,MATCH($A16,'Angle Plans'!$A$5:$A$7,0))) -> 2000 | N16: =IF($C16="EE",INDEX('Angle Plans'!$E$5:$E$7,MATCH($A16,'Angle Plans'!$A$5:$A$7,0)),INDEX('Angle Plans'!$F$5:$F$7,MATCH($A16,'Angle Plans'!$A$5:$A$7,0))) -> 4000 | O16: =$L16+$N16 -> 12323.32 | P16: =$I16*$D16*12 -> 16646.64 | Q16: =$A16&"|"&$C16 -> ANG TRAD 1000/2000|FAM
A18: HSA funding is deliberately not modeled. On the HDHP 3400/5000 an employee can pay part of that worst case with pretax dollars, so the real cost is lower - but by an amount only the employee controls.
A19: 'Onyx $/yr (all enrolled)' multiplies by how many people sit in that tier, so the column sums to Onyx's whole medical spend.

Sheet By Employee
A1: Every Angle plan, priced for each person
A2: Driven by the enrollment table on the Contributions tab. Anyone marked No shows a blank deduction - change them to Yes to price them in.
A4: Employee | B4: Enrolling? | C4: Tier | D4: Code | E4: Plan | F4: Monthly premium | G4: Onyx pays $/mo | H4: Employee $/mo | I4: Employee $/yr | J4: Deductible | K4: OOP max | L4: Worst case $/yr
A5: Steven Nikolov | B5: =Contributions!$E$22 -> Yes | C5: Family | D5: FAM | E5: ANG HDHP 3400/5000 | F5: =INDEX('Cost by Tier'!$E$5:$E$16,MATCH($E5&"|"&$D5,CostKey,0)) -> 1361 | G5: =INDEX('Cost by Tier'!$H$5:$H$16,MATCH($E5&"|"&$D5,CostKey,0)) -> 1000 | H5: =INDEX('Cost by Tier'!$I$5:$I$16,MATCH($E5&"|"&$D5,CostKey,0)) -> 361 | I5: =INDEX('Cost by Tier'!$L$5:$L$16,MATCH($E5&"|"&$D5,CostKey,0)) -> 4332 | J5: =INDEX('Cost by Tier'!$M$5:$M$16,MATCH($E5&"|"&$D5,CostKey,0)) -> 6800 | K5: =INDEX('Cost by Tier'!$N$5:$N$16,MATCH($E5&"|"&$D5,CostKey,0)) -> 10000 | L5: =INDEX('Cost by Tier'!$O$5:$O$16,MATCH($E5&"|"&$D5,CostKey,0)) -> 14332
A6: Steven Nikolov | B6: =Contributions!$E$22 -> Yes | C6: Family | D6: FAM | E6: ANG TRAD 2000/4000 | F6: =INDEX('Cost by Tier'!$E$5:$E$16,MATCH($E6&"|"&$D6,CostKey,0)) -> 1525.54 | G6: =INDEX('Cost by Tier'!$H$5:$H$16,MATCH($E6&"|"&$D6,CostKey,0)) -> 1000 | H6: =INDEX('Cost by Tier'!$I$5:$I$16,MATCH($E6&"|"&$D6,CostKey,0)) -> 525.54 | I6: =INDEX('Cost by Tier'!$L$5:$L$16,MATCH($E6&"|"&$D6,CostKey,0)) -> 6306.48 | J6: =INDEX('Cost by Tier'!$M$5:$M$16,MATCH($E6&"|"&$D6,CostKey,0)) -> 4000 | K6: =INDEX('Cost by Tier'!$N$5:$N$16,MATCH($E6&"|"&$D6,CostKey,0)) -> 8000 | L6: =INDEX('Cost by Tier'!$O$5:$O$16,MATCH($E6&"|"&$D6,CostKey,0)) -> 14306.48
A7: Steven Nikolov | B7: =Contributions!$E$22 -> Yes | C7: Family | D7: FAM | E7: ANG TRAD 1000/2000 | F7: =INDEX('Cost by Tier'!$E$5:$E$16,MATCH($E7&"|"&$D7,CostKey,0)) -> 1693.61 | G7: =INDEX('Cost by Tier'!$H$5:$H$16,MATCH($E7&"|"&$D7,CostKey,0)) -> 1000 | H7: =INDEX('Cost by Tier'!$I$5:$I$16,MATCH($E7&"|"&$D7,CostKey,0)) -> 693.61 | I7: =INDEX('Cost by Tier'!$L$5:$L$16,MATCH($E7&"|"&$D7,CostKey,0)) -> 8323.32 | J7: =INDEX('Cost by Tier'!$M$5:$M$16,MATCH($E7&"|"&$D7,CostKey,0)) -> 2000 | K7: =INDEX('Cost by Tier'!$N$5:$N$16,MATCH($E7&"|"&$D7,CostKey,0)) -> 4000 | L7: =INDEX('Cost by Tier'!$O$5:$O$16,MATCH($E7&"|"&$D7,CostKey,0)) -> 12323.32
A8: Lisa Danforth | B8: =Contributions!$E$23 -> Yes | C8: Employee only | D8: EE | E8: ANG HDHP 3400/5000 | F8: =INDEX('Cost by Tier'!$E$5:$E$16,MATCH($E8&"|"&$D8,CostKey,0)) -> 439.03 | G8: =INDEX('Cost by Tier'!$H$5:$H$16,MATCH($E8&"|"&$D8,CostKey,0)) -> 300 | H8: =INDEX('Cost by Tier'!$I$5:$I$16,MATCH($E8&"|"&$D8,CostKey,0)) -> 139.03 | I8: =INDEX('Cost by Tier'!$L$5:$L$16,MATCH($E8&"|"&$D8,CostKey,0)) -> 1668.36 | J8: =INDEX('Cost by Tier'!$M$5:$M$16,MATCH($E8&"|"&$D8,CostKey,0)) -> 3400 | K8: =INDEX('Cost by Tier'!$N$5:$N$16,MATCH($E8&"|"&$D8,CostKey,0)) -> 5000 | L8: =INDEX('Cost by Tier'!$O$5:$O$16,MATCH($E8&"|"&$D8,CostKey,0)) -> 6668.36
A9: Lisa Danforth | B9: =Contributions!$E$23 -> Yes | C9: Employee only | D9: EE | E9: ANG TRAD 2000/4000 | F9: =INDEX('Cost by Tier'!$E$5:$E$16,MATCH($E9&"|"&$D9,CostKey,0)) -> 492.11 | G9: =INDEX('Cost by Tier'!$H$5:$H$16,MATCH($E9&"|"&$D9,CostKey,0)) -> 300 | H9: =INDEX('Cost by Tier'!$I$5:$I$16,MATCH($E9&"|"&$D9,CostKey,0)) -> 192.11 | I9: =INDEX('Cost by Tier'!$L$5:$L$16,MATCH($E9&"|"&$D9,CostKey,0)) -> 2305.32 | J9: =INDEX('Cost by Tier'!$M$5:$M$16,MATCH($E9&"|"&$D9,CostKey,0)) -> 2000 | K9: =INDEX('Cost by Tier'!$N$5:$N$16,MATCH($E9&"|"&$D9,CostKey,0)) -> 4000 | L9: =INDEX('Cost by Tier'!$O$5:$O$16,MATCH($E9&"|"&$D9,CostKey,0)) -> 6305.32
A10: Lisa Danforth | B10: =Contributions!$E$23 -> Yes | C10: Employee only | D10: EE | E10: ANG TRAD 1000/2000 | F10: =INDEX('Cost by Tier'!$E$5:$E$16,MATCH($E10&"|"&$D10,CostKey,0)) -> 546.33 | G10: =INDEX('Cost by Tier'!$H$5:$H$16,MATCH($E10&"|"&$D10,CostKey,0)) -> 300 | H10: =INDEX('Cost by Tier'!$I$5:$I$16,MATCH($E10&"|"&$D10,CostKey,0)) -> 246.33 | I10: =INDEX('Cost by Tier'!$L$5:$L$16,MATCH($E10&"|"&$D10,CostKey,0)) -> 2955.96 | J10: =INDEX('Cost by Tier'!$M$5:$M$16,MATCH($E10&"|"&$D10,CostKey,0)) -> 1000 | K10: =INDEX('Cost by Tier'!$N$5:$N$16,MATCH($E10&"|"&$D10,CostKey,0)) -> 2000 | L10: =INDEX('Cost by Tier'!$O$5:$O$16,MATCH($E10&"|"&$D10,CostKey,0)) -> 4955.96
A11: Jessica Bumphus | B11: =Contributions!$E$24 -> Yes | C11: Family | D11: FAM | E11: ANG HDHP 3400/5000 | F11: =INDEX('Cost by Tier'!$E$5:$E$16,MATCH($E11&"|"&$D11,CostKey,0)) -> 1361 | G11: =INDEX('Cost by Tier'!$H$5:$H$16,MATCH($E11&"|"&$D11,CostKey,0)) -> 1000 | H11: =INDEX('Cost by Tier'!$I$5:$I$16,MATCH($E11&"|"&$D11,CostKey,0)) -> 361 | I11: =INDEX('Cost by Tier'!$L$5:$L$16,MATCH($E11&"|"&$D11,CostKey,0)) -> 4332 | J11: =INDEX('Cost by Tier'!$M$5:$M$16,MATCH($E11&"|"&$D11,CostKey,0)) -> 6800 | K11: =INDEX('Cost by Tier'!$N$5:$N$16,MATCH($E11&"|"&$D11,CostKey,0)) -> 10000 | L11: =INDEX('Cost by Tier'!$O$5:$O$16,MATCH($E11&"|"&$D11,CostKey,0)) -> 14332
A12: Jessica Bumphus | B12: =Contributions!$E$24 -> Yes | C12: Family | D12: FAM | E12: ANG TRAD 2000/4000 | F12: =INDEX('Cost by Tier'!$E$5:$E$16,MATCH($E12&"|"&$D12,CostKey,0)) -> 1525.54 | G12: =INDEX('Cost by Tier'!$H$5:$H$16,MATCH($E12&"|"&$D12,CostKey,0)) -> 1000 | H12: =INDEX('Cost by Tier'!$I$5:$I$16,MATCH($E12&"|"&$D12,CostKey,0)) -> 525.54 | I12: =INDEX('Cost by Tier'!$L$5:$L$16,MATCH($E12&"|"&$D12,CostKey,0)) -> 6306.48 | J12: =INDEX('Cost by Tier'!$M$5:$M$16,MATCH($E12&"|"&$D12,CostKey,0)) -> 4000 | K12: =INDEX('Cost by Tier'!$N$5:$N$16,MATCH($E12&"|"&$D12,CostKey,0)) -> 8000 | L12: =INDEX('Cost by Tier'!$O$5:$O$16,MATCH($E12&"|"&$D12,CostKey,0)) -> 14306.48
A13: Jessica Bumphus | B13: =Contributions!$E$24 -> Yes | C13: Family | D13: FAM | E13: ANG TRAD 1000/2000 | F13: =INDEX('Cost by Tier'!$E$5:$E$16,MATCH($E13&"|"&$D13,CostKey,0)) -> 1693.61 | G13: =INDEX('Cost by Tier'!$H$5:$H$16,MATCH($E13&"|"&$D13,CostKey,0)) -> 1000 | H13: =INDEX('Cost by Tier'!$I$5:$I$16,MATCH($E13&"|"&$D13,CostKey,0)) -> 693.61 | I13: =INDEX('Cost by Tier'!$L$5:$L$16,MATCH($E13&"|"&$D13,CostKey,0)) -> 8323.32 | J13: =INDEX('Cost by Tier'!$M$5:$M$16,MATCH($E13&"|"&$D13,CostKey,0)) -> 2000 | K13: =INDEX('Cost by Tier'!$N$5:$N$16,MATCH($E13&"|"&$D13,CostKey,0)) -> 4000 | L13: =INDEX('Cost by Tier'!$O$5:$O$16,MATCH($E13&"|"&$D13,CostKey,0)) -> 12323.32
A14: Christine Johnson | B14: =Contributions!$E$25 -> Yes | C14: Employee + spouse | D14: ES | E14: ANG HDHP 3400/5000 | F14: =INDEX('Cost by Tier'!$E$5:$E$16,MATCH($E14&"|"&$D14,CostKey,0)) -> 921.97 | G14: =INDEX('Cost by Tier'!$H$5:$H$16,MATCH($E14&"|"&$D14,CostKey,0)) -> 600 | H14: =INDEX('Cost by Tier'!$I$5:$I$16,MATCH($E14&"|"&$D14,CostKey,0)) -> 321.97 | I14: =INDEX('Cost by Tier'!$L$5:$L$16,MATCH($E14&"|"&$D14,CostKey,0)) -> 3863.64 | J14: =INDEX('Cost by Tier'!$M$5:$M$16,MATCH($E14&"|"&$D14,CostKey,0)) -> 6800 | K14: =INDEX('Cost by Tier'!$N$5:$N$16,MATCH($E14&"|"&$D14,CostKey,0)) -> 10000 | L14: =INDEX('Cost by Tier'!$O$5:$O$16,MATCH($E14&"|"&$D14,CostKey,0)) -> 13863.64
A15: Christine Johnson | B15: =Contributions!$E$25 -> Yes | C15: Employee + spouse | D15: ES | E15: ANG TRAD 2000/4000 | F15: =INDEX('Cost by Tier'!$E$5:$E$16,MATCH($E15&"|"&$D15,CostKey,0)) -> 1033.43 | G15: =INDEX('Cost by Tier'!$H$5:$H$16,MATCH($E15&"|"&$D15,CostKey,0)) -> 600 | H15: =INDEX('Cost by Tier'!$I$5:$I$16,MATCH($E15&"|"&$D15,CostKey,0)) -> 433.43 | I15: =INDEX('Cost by Tier'!$L$5:$L$16,MATCH($E15&"|"&$D15,CostKey,0)) -> 5201.16 | J15: =INDEX('Cost by Tier'!$M$5:$M$16,MATCH($E15&"|"&$D15,CostKey,0)) -> 4000 | K15: =INDEX('Cost by Tier'!$N$5:$N$16,MATCH($E15&"|"&$D15,CostKey,0)) -> 8000 | L15: =INDEX('Cost by Tier'!$O$5:$O$16,MATCH($E15&"|"&$D15,CostKey,0)) -> 13201.16
A16: Christine Johnson | B16: =Contributions!$E$25 -> Yes | C16: Employee + spouse | D16: ES | E16: ANG TRAD 1000/2000 | F16: =INDEX('Cost by Tier'!$E$5:$E$16,MATCH($E16&"|"&$D16,CostKey,0)) -> 1147.29 | G16: =INDEX('Cost by Tier'!$H$5:$H$16,MATCH($E16&"|"&$D16,CostKey,0)) -> 600 | H16: =INDEX('Cost by Tier'!$I$5:$I$16,MATCH($E16&"|"&$D16,CostKey,0)) -> 547.29 | I16: =INDEX('Cost by Tier'!$L$5:$L$16,MATCH($E16&"|"&$D16,CostKey,0)) -> 6567.48 | J16: =INDEX('Cost by Tier'!$M$5:$M$16,MATCH($E16&"|"&$D16,CostKey,0)) -> 2000 | K16: =INDEX('Cost by Tier'!$N$5:$N$16,MATCH($E16&"|"&$D16,CostKey,0)) -> 4000 | L16: =INDEX('Cost by Tier'!$O$5:$O$16,MATCH($E16&"|"&$D16,CostKey,0)) -> 10567.48
A17: Josephine Mack | B17: =Contributions!$E$26 -> No | C17: Family | D17: FAM | E17: ANG HDHP 3400/5000 | F17: =INDEX('Cost by Tier'!$E$5:$E$16,MATCH($E17&"|"&$D17,CostKey,0)) -> 1361 | G17: =INDEX('Cost by Tier'!$H$5:$H$16,MATCH($E17&"|"&$D17,CostKey,0)) -> 1000 | H17: =INDEX('Cost by Tier'!$I$5:$I$16,MATCH($E17&"|"&$D17,CostKey,0)) -> 361 | I17: =INDEX('Cost by Tier'!$L$5:$L$16,MATCH($E17&"|"&$D17,CostKey,0)) -> 4332 | J17: =INDEX('Cost by Tier'!$M$5:$M$16,MATCH($E17&"|"&$D17,CostKey,0)) -> 6800 | K17: =INDEX('Cost by Tier'!$N$5:$N$16,MATCH($E17&"|"&$D17,CostKey,0)) -> 10000 | L17: =INDEX('Cost by Tier'!$O$5:$O$16,MATCH($E17&"|"&$D17,CostKey,0)) -> 14332
A18: Josephine Mack | B18: =Contributions!$E$26 -> No | C18: Family | D18: FAM | E18: ANG TRAD 2000/4000 | F18: =INDEX('Cost by Tier'!$E$5:$E$16,MATCH($E18&"|"&$D18,CostKey,0)) -> 1525.54 | G18: =INDEX('Cost by Tier'!$H$5:$H$16,MATCH($E18&"|"&$D18,CostKey,0)) -> 1000 | H18: =INDEX('Cost by Tier'!$I$5:$I$16,MATCH($E18&"|"&$D18,CostKey,0)) -> 525.54 | I18: =INDEX('Cost by Tier'!$L$5:$L$16,MATCH($E18&"|"&$D18,CostKey,0)) -> 6306.48 | J18: =INDEX('Cost by Tier'!$M$5:$M$16,MATCH($E18&"|"&$D18,CostKey,0)) -> 4000 | K18: =INDEX('Cost by Tier'!$N$5:$N$16,MATCH($E18&"|"&$D18,CostKey,0)) -> 8000 | L18: =INDEX('Cost by Tier'!$O$5:$O$16,MATCH($E18&"|"&$D18,CostKey,0)) -> 14306.48
A19: Josephine Mack | B19: =Contributions!$E$26 -> No | C19: Family | D19: FAM | E19: ANG TRAD 1000/2000 | F19: =INDEX('Cost by Tier'!$E$5:$E$16,MATCH($E19&"|"&$D19,CostKey,0)) -> 1693.61 | G19: =INDEX('Cost by Tier'!$H$5:$H$16,MATCH($E19&"|"&$D19,CostKey,0)) -> 1000 | H19: =INDEX('Cost by Tier'!$I$5:$I$16,MATCH($E19&"|"&$D19,CostKey,0)) -> 693.61 | I19: =INDEX('Cost by Tier'!$L$5:$L$16,MATCH($E19&"|"&$D19,CostKey,0)) -> 8323.32 | J19: =INDEX('Cost by Tier'!$M$5:$M$16,MATCH($E19&"|"&$D19,CostKey,0)) -> 2000 | K19: =INDEX('Cost by Tier'!$N$5:$N$16,MATCH($E19&"|"&$D19,CostKey,0)) -> 4000 | L19: =INDEX('Cost by Tier'!$O$5:$O$16,MATCH($E19&"|"&$D19,CostKey,0)) -> 12323.32

Sheet Questco
A1: Questco - PEO services other than medical
A2: IRS-Certified PEO. Quote dated for 5 worksite employees on $658,322 of annual payroll. Medical is declined - Onyx takes Angle instead.
A4: 1. WHAT ONYX PAYS QUESTCO (payroll taxes are separate - see block 3)
A5: Cost line | B5: Basis | C5: Rate / amount | D5: Headcount | E5: Elected? | F5: Monthly | G5: Annual | H5: Note
A6: Administrative fee | B6: Per active employee per month | C6: 117 | D6: 5 | E6: Required | F6: =G6/12 -> 585 | G6: =C6*D6*12 -> 7020 | H6: The core PEO fee. $117 PEPM as quoted.
A7: Workers' compensation + EPLI | B7: Annual premium | C7: 1402.13 | E7: Required | F7: =G7/12 -> 116.84417 | G7: =IF($E7="No",0,$C7) -> 1402.13 | H7: Subject to full underwriting - loss runs, class-code confirmation, possible survey. The rate can move.
A8: Cyber liability | B8: Annual premium | C8: 420 | E8: No | F8: =G8/12 -> 0 | G8: =IF($E8="No",0,$C8) -> 0 | H8: $250,000 aggregate, $1,000 per-claim retention, $50,000 sub-limits. Set to No - Onyx is placing cyber separately. A standalone policy is the right call for a firm holding client tax data under the FTC Safeguards Rule and IRS Pub 4557.
A9: Recurring subtotal | F9: =SUM(F6:F8) -> 701.84417 | G9: =SUM(G6:G8) -> 8422.13
A10: Payroll installation / implementation | B10: One time, first year only | G10: 1000
A11: The 401(k) is on its own tab. Questco charges Onyx nothing for it unless Onyx matches.
A13: 2. OPTIONAL EMPLOYER-PAID BENEFITS <- set Yes / No
A14: Benefit | B14: Elected? | C14: Design | D14: Monthly | E14: Annual | F14: Note
A15: Basic life & AD&D | B15: Yes | C15: $50,000 flat | D15: 46.25 | E15: =IF($B15="Yes",$D15*12,0) -> 555 | F15: $50,000 is exactly the IRC 79 exclusion limit. Going to 1x salary would create imputed W-2 income for Steven, Lisa and Jessica and cost about $1,100 more. Steven's is taxable either way as a >2% shareholder.
A16: Long-term disability | B16: Yes | C16: 60% to $10,000/mo, 90-day elimination | D16: 159.09 | E16: =IF($B16="Yes",$D16*12,0) -> 1909.08 | F16: The $15,000 tier is priced identically because nobody's 60% benefit reaches it - Steven's is the highest at $9,300. At $5,000 the three highest earners would be underinsured.
A17: Short-term disability | B17: No | C17: 60% to $1,500/wk, 7/14, 13 weeks | D17: 126.74 | E17: =IF($B17="Yes",$D17*12,0) -> 0 | F17: Onyx's stated benefit design has STD employee-paid. Set to Yes to model Onyx funding it.
A18: Elected ancillary subtotal | D18: =SUM(E15:E17)/12 -> 205.34 | E18: =SUM(E15:E17) -> 2464.08
A19: Rates are estimates from the Questco ancillary comparison - final rates come from the salaries in payroll. Dental and vision are employee-paid and are not in this model.
A21: 3. PAYROLL TAXES (Onyx owes these with or without a PEO - shown so the invoice reconciles, NOT as a cost of choosing Questco)
A22: Tax | B22: Quoted annual | C22: Note
A23: FICA - employer share | B23: 50665.81 | C23: Quoted figure exceeds 7.65% of $658,322 ($50,361.63) and does not appear to cap Social Security at the wage base. With Steven at $186,000 and Lisa at $178,094 it should be lower, not higher. Ask Questco what base was used.
A24: FUTA | B24: 210 | C24: 5 employees x $7,000 x 0.6%. Ties exactly.
A25: SUTA (Arizona) | B25: 1300 | C25: Confirm whether Arizona reporting is at client level or PEO level - it decides whether Onyx keeps its own experience rating on exit.
A26: Pass-through subtotal | B26: =SUM(B23:B25) -> 52175.81
A28: 4. WHAT THE FEE BUYS
A29: Category | B29: Included | C29: Relevance to Onyx
A30: Payroll administration | B30: Processing, direct deposit, garnishments, state and federal tax remittance, Forms 940/941, W-2/W-3, PTO tracking, ACA reporting, 20+ standard reports. Payroll runs 3 business days before payday and Onyx controls entry. | C30: Core. Replaces the payroll function outright.
A31: HR expertise and support | B31: Dedicated HR team, handbook and policy review, job descriptions, onboarding, employee relations, terminations, unemployment claims, EEOC, FMLA and FLSA compliance. | C31: High. Displaces the outside HR support Onyx pays for today.
A32: Benefits administration | B32: Enrollments, terminations, qualifying events, COBRA, Section 125 compliance, creditable coverage reporting, claims advocacy, and in-house invoice reconciliation for client-owned plans. | C32: High - and the reason Questco can administer the Angle plan.
A33: Self-funded plan filings | B33: PCORI fee calculation and Form 720; Forms 1094-B/1095-B. | C33: CRITICAL. Angle is level funded, so these are now Onyx's obligations. Confirm in writing that Questco covers them for the Angle plan by name.
A34: Workers' compensation | B34: Coverage at PEO rates, safety training and materials, claims handling. | C34: Medium. Office exposure is low, but the rate is still subject to underwriting.
A35: 401(k) | B35: Large-group multiple employer plan, $3.00 per participating employee per quarter, no employer cost unless Onyx matches. Confirmed it does not require annual re-signature by Onyx. | C35: High. See the 401(k) tab - the match is the only part Onyx controls.
A36: Cyber liability | B36: $250,000 annual aggregate, $1,000 per-claim retention, $50,000 sub-limits, 24/7 incident hotline. | C36: Declined - Onyx is placing a standalone policy instead.
A37: CPEO status | B37: IRS-Certified Professional Employer Organization. | C37: High. It is what protects the payroll-tax wage bases from restarting on a mid-year start - worth roughly $5,600 given Steven's and Lisa's salaries. Confirm it.
A38: HR technology | B38: Employee self-service portal, mobile access, reporting and analytics. | C38: Medium.

Sheet 401(k)
A1: 401(k) through Questco - match modelling
A2: Questco charges $3.00 per participating employee per quarter and nothing to Onyx unless Onyx chooses to match. A match is NOT required - see block 4. Everything below is a lever.
A3: EDIT THE YELLOW CELLS.
A5: 1. PLAN SETTINGS
A6: Setting | C6: Value | D6: Per / of pay | E6: Note
A7: Per-participant fee | C7: 3 | D7: per quarter | E7: Questco's quoted fee - $12 a year per participant.
A8: Fee paid by | C8: Participant | E8: Set to Employer to have Onyx absorb it. Questco's statement is that Onyx pays nothing unless it matches, so Participant is the default - worth confirming.
A9: IRS compensation limit | C9: 350000 | E9: CONFIRM the current-year 401(a)(17) figure. Nobody here is close, so it does not bind.
A10: IRS elective deferral limit | C10: 24000 | E10: CONFIRM the current-year 402(g) figure. Not binding at the deferral rates below.
A12: Match type | C12: None | E12: None, Tiered match, or Non-elective. Defaults to None because nothing has been committed. Block 3 prices all three at once.
A13: Tier 1 - match rate | C13: 1 | D13: 0.03 | E13: Match 100% of the first 3% of pay deferred. With Tier 2 this is the safe harbor basic formula.
A14: Tier 2 - match rate | C14: 0.5 | D14: 0.02 | E14: Match 50% of the next 2% of pay. Anyone deferring 5% or more earns the full 4% of pay.
A15: Non-elective rate | C15: 0.03 | E15: Used only when Match type is Non-elective. 3% of pay to every participating employee, whether or not they defer.
A17: 2. WHO PARTICIPATES AND WHAT THEY DEFER
A18: Employee | B18: Eligible pay | C18: Participating? | D18: Deferral % of pay | E18: Employee deferral $/yr | F18: Onyx match $/yr (selected type) | G18: Match as % of pay | H18: Participant fee $/yr | I18: IF safe harbor match | J18: IF 3% non-elective
A19: Steven Nikolov | B19: 186000 | C19: Yes | D19: 0.06 | E19: =IF($C19<>"Yes",0,MIN(MIN($B19,$C$9)*$D19,$C$10)) -> 11160 | F19: =IF($C19<>"Yes",0,IF($C$12="None",0,IF($C$12="Non-elective",$J19,$I19))) -> 0 | G19: =IF($B19=0,0,$F19/$B19) -> 0 | H19: =IF($C19<>"Yes",0,$C$7*4) -> 12 | I19: =IF($C19<>"Yes",0,MIN($B19,$C$9)*($C$13*MIN($D19,$D$13)+$C$14*MIN(MAX($D19-$D$13,0),$D$14))) -> 7440 | J19: =IF($C19<>"Yes",0,MIN($B19,$C$9)*$C$15) -> 5580
A20: Lisa Danforth | B20: 178094 | C20: Yes | D20: 0.06 | E20: =IF($C20<>"Yes",0,MIN(MIN($B20,$C$9)*$D20,$C$10)) -> 10685.64 | F20: =IF($C20<>"Yes",0,IF($C$12="None",0,IF($C$12="Non-elective",$J20,$I20))) -> 0 | G20: =IF($B20=0,0,$F20/$B20) -> 0 | H20: =IF($C20<>"Yes",0,$C$7*4) -> 12 | I20: =IF($C20<>"Yes",0,MIN($B20,$C$9)*($C$13*MIN($D20,$D$13)+$C$14*MIN(MAX($D20-$D$13,0),$D$14))) -> 7123.76 | J20: =IF($C20<>"Yes",0,MIN($B20,$C$9)*$C$15) -> 5342.82
A21: Jessica Bumphus | B21: 135000 | C21: Yes | D21: 0.06 | E21: =IF($C21<>"Yes",0,MIN(MIN($B21,$C$9)*$D21,$C$10)) -> 8100 | F21: =IF($C21<>"Yes",0,IF($C$12="None",0,IF($C$12="Non-elective",$J21,$I21))) -> 0 | G21: =IF($B21=0,0,$F21/$B21) -> 0 | H21: =IF($C21<>"Yes",0,$C$7*4) -> 12 | I21: =IF($C21<>"Yes",0,MIN($B21,$C$9)*($C$13*MIN($D21,$D$13)+$C$14*MIN(MAX($D21-$D$13,0),$D$14))) -> 5400 | J21: =IF($C21<>"Yes",0,MIN($B21,$C$9)*$C$15) -> 4050
A22: Christine Johnson | B22: 79228 | C22: Yes | D22: 0.06 | E22: =IF($C22<>"Yes",0,MIN(MIN($B22,$C$9)*$D22,$C$10)) -> 4753.68 | F22: =IF($C22<>"Yes",0,IF($C$12="None",0,IF($C$12="Non-elective",$J22,$I22))) -> 0 | G22: =IF($B22=0,0,$F22/$B22) -> 0 | H22: =IF($C22<>"Yes",0,$C$7*4) -> 12 | I22: =IF($C22<>"Yes",0,MIN($B22,$C$9)*($C$13*MIN($D22,$D$13)+$C$14*MIN(MAX($D22-$D$13,0),$D$14))) -> 3169.12 | J22: =IF($C22<>"Yes",0,MIN($B22,$C$9)*$C$15) -> 2376.84
A23: Josephine Mack | B23: 80000 | C23: Yes | D23: 0.06 | E23: =IF($C23<>"Yes",0,MIN(MIN($B23,$C$9)*$D23,$C$10)) -> 4800 | F23: =IF($C23<>"Yes",0,IF($C$12="None",0,IF($C$12="Non-elective",$J23,$I23))) -> 0 | G23: =IF($B23=0,0,$F23/$B23) -> 0 | H23: =IF($C23<>"Yes",0,$C$7*4) -> 12 | I23: =IF($C23<>"Yes",0,MIN($B23,$C$9)*($C$13*MIN($D23,$D$13)+$C$14*MIN(MAX($D23-$D$13,0),$D$14))) -> 3200 | J23: =IF($C23<>"Yes",0,MIN($B23,$C$9)*$C$15) -> 2400
A24: TOTAL | B24: =SUM(B19:B23) -> 658322 | C24: =COUNTIF(C19:C23,"Yes")&" in" -> 5 in | E24: =SUM(E19:E23) -> 39499.32 | F24: =SUM(F19:F23) -> 0 | G24: =IF(B24=0,0,F24/B24) -> 0 | H24: =SUM(H19:H23) -> 60 | I24: =SUM(I19:I23) -> 26332.88 | J24: =SUM(J19:J23) -> 19749.66
A25: Deferral rates default to 6%, which fully earns the safe harbor basic match. Nobody has elected anything yet - this is an assumption, and it is what drives the two right-hand columns.
A27: 3. THE THREE OPTIONS, PRICED SIDE BY SIDE
A28: Option | B28: Onyx cost $/yr | C28: Onyx cost $/mo | D28: What it buys
A29: No employer contribution | B29: 0 | C29: =B29/12 -> 0 | D29: Cheapest. But the plan is then subject to nondiscrimination testing every year, and once it becomes top-heavy Onyx owes the minimum anyway.
A30: Safe harbor basic match (100% of first 3%, 50% of next 2%) | B30: =I24 -> 26332.88 | C30: =B30/12 -> 2194.4067 | D30: Exempts the plan from nondiscrimination testing and, on its own, from the top-heavy minimum. Only the people who defer receive it.
A31: Safe harbor 3% non-elective | B31: =J24 -> 19749.66 | C31: =B31/12 -> 1645.805 | D31: Same exemptions. Goes to every participating employee whether or not they defer, so it costs Onyx money for non-savers.
A33: 4. WHAT ONYX IS ACTUALLY COSTED AT, GIVEN THE MATCH TYPE ABOVE
A34: Line | B34: Monthly | C34: Annual | D34: Note
A35: Employer match / non-elective | B35: =C35/12 -> 0 | C35: =F24 -> 0 | D35: Deductible to Onyx. Unlike health premiums, a contribution for Steven as a >2% S-corp shareholder is a normal deductible plan contribution, not W-2 wages.
A36: Participant fees absorbed by Onyx | B36: =C36/12 -> 0 | C36: =IF($C$8="Employer",H24,0) -> 0 | D36: Zero while the fee sits on participants.
A37: ONYX 401(k) COST | B37: =SUM(B35:B36) -> 0 | C37: =SUM(C35:C36) -> 0
A39: 5. IS A MATCH REQUIRED? No - but read this before choosing None
A40: • NO LAW REQUIRES AN EMPLOYER MATCH. A 401(k) can be deferral-only, funded entirely by employees. Questco's fee does not change either way.
A41: • Two testing rules can still force money in. Nondiscrimination testing compares what the highly compensated defer against what everyone else defers; if the gap is too wide, the highly compensated get deferrals refunded. Steven is highly compensated by ownership and Lisa very likely by pay, so two of five would sit on that side of the test. (The IRS calls these the ADP and ACP tests - an actuarial term that has nothing to do with the payroll company of the same initials.)
A42: • Top-heavy: when key employees hold more than 60% of plan assets, the employer owes a minimum contribution of up to 3% of pay to every non-key employee. With Steven owning 100% this plan is likely to go top-heavy - though usually not in year one, since the test looks at the prior year end and a new plan starts at zero.
A43: • A safe harbor design - the basic match or the 3% non-elective - buys exemption from nondiscrimination testing, and from the top-heavy minimum when the safe harbor contribution is the only employer money in the plan. That is the real trade: a known, capped cost instead of an uncertain one.
A44: • So the practical choice is not match or no match. It is: accept testing and a probable top-heavy bill later, or take a safe harbor now and know the number. Block 3 prices both safe harbor routes.
A45: • Confirm the current-year compensation, deferral and highly-compensated thresholds, and the top-heavy position, with the plan's third-party administrator before adopting.
A46: • Ask Questco whether an adopting employer in their multiple employer plan still claims the SECURE 2.0 start-up credits - up to $5,000/yr for three years plus $500/yr for auto-enrolment. Still unanswered.

Sheet Combined
A1: Angle + Questco - monthly and annual projection
A2: Everything here recalculates from the Contributions, Questco and 401(k) tabs. Pick a plan below to drive the first two blocks.
A4: SELECTED ANGLE PLAN | C4: ANG HDHP 3400/5000
A6: 1. WHAT ONYX PAYS
A7: Cost line | B7: Vendor | C7: Monthly | D7: Annual | E7: Note
A8: Medical - employer contribution | B8: Angle / CapFi | C8: =SUMIFS('Cost by Tier'!$K$5:$K$16,'Cost by Tier'!$A$5:$A$16,$C$4)/12 -> 2900 | D8: =SUMIFS('Cost by Tier'!$K$5:$K$16,'Cost by Tier'!$A$5:$A$16,$C$4) -> 34800 | E8: Fixed dollars per tier. Does not move when an employee changes plans.
A9: Administrative fee | B9: Questco | C9: =Questco!F6 -> 585 | D9: =Questco!G6 -> 7020 | E9: $117 per employee per month.
A10: Workers' comp + EPLI | B10: Questco | C10: =Questco!F7 -> 116.84417 | D10: =Questco!G7 -> 1402.13 | E10: Subject to underwriting.
A11: Cyber liability | B11: Questco | C11: =Questco!F8 -> 0 | D11: =Questco!G8 -> 0 | E11: Zero while it is set to No on the Questco tab. Onyx is placing this separately.
A12: Employer-paid ancillary | B12: Questco | C12: =Questco!D18 -> 205.34 | D12: =Questco!E18 -> 2464.08 | E12: Life, LTD and STD as elected on the Questco tab.
A13: 401(k) - employer cost | B13: Questco | C13: ='401(k)'!B37 -> 0 | D13: ='401(k)'!C37 -> 0 | E13: Match, plus participant fees only if Onyx absorbs them. Set the formula on the 401(k) tab.
A14: ONYX RECURRING TOTAL | C14: =SUM(C8:C13) -> 3807.1842 | D14: =SUM(D8:D13) -> 45686.21
A15: Implementation (first year only) | B15: Questco | D15: =Questco!G10 -> 1000
A16: ONYX FIRST-YEAR TOTAL | D16: =D14+D15 -> 46686.21
A17: The 401(k) line is a MODELLED match, not a committed cost. At the default settings - safe harbor basic, everyone deferring 6% - it is the largest line on this page after medical. Set Match type to None on the 401(k) tab to see Onyx's cost without a match.
A18: Payroll taxes of about $52,176 a year are NOT in this total. Onyx owes FICA, FUTA and SUTA whether or not there is a PEO, so they are a pass-through on the Questco invoice rather than a cost of the relationship. They are itemised on the Questco tab.
A20: 2. WHAT THE EMPLOYEES PAY, AND THE COMBINED PICTURE
A21: Line | B21: Monthly | C21: Annual | D21: Note
A22: Employee medical deductions, all enrolled | B22: =SUMIFS('Cost by Tier'!$P$5:$P$16,'Cost by Tier'!$A$5:$A$16,$C$4)/12 -> 1183 | C22: =SUMIFS('Cost by Tier'!$P$5:$P$16,'Cost by Tier'!$A$5:$A$16,$C$4) -> 14196 | D22: Premium only. Pretax for everyone except Steven.
A23: Employee 401(k) deferrals | B23: ='401(k)'!E24/12 -> 3291.61 | C23: ='401(k)'!E24 -> 39499.32 | D23: Their own savings, not a cost - shown so the payroll picture is complete.
A24: Employee 401(k) fees | B24: =IF('401(k)'!$C$8="Employer",0,'401(k)'!H24/12) -> 5 | C24: =IF('401(k)'!$C$8="Employer",0,'401(k)'!H24) -> 60 | D24: $3 per quarter each while the fee sits on participants.
A25: Onyx + employees, medical premium only | B25: =C8+B22 -> 4083 | C25: =D8+C22 -> 48996 | D25: The true cost of the Angle plan itself, both sides.
A26: Onyx + employees, all in | B26: =C14+B22+B24 -> 4995.1842 | C26: =D14+C22+C24 -> 59942.21 | D26: Adds the Questco fee, elected ancillary, the 401(k) and the participant fees.
A27: Combined worst case, one bad year | C27: =D14+SUMPRODUCT(('Cost by Tier'!$A$5:$A$16=$C$4)*'Cost by Tier'!$O$5:$O$16*'Cost by Tier'!$D$5:$D$16) -> 94882.21 | D27: Assumes every enrolled household hits its out-of-pocket maximum in the same year. A ceiling, not a forecast.
A29: 3. ALL THREE PLANS SIDE BY SIDE (annual, at the current settings)
A30: Angle plan | B30: HSA | C30: Onyx - medical | D30: Onyx - all in | E30: Employee medical | F30: Onyx + employees | G30: Combined worst case
A31: ANG HDHP 3400/5000 | B31: Y | C31: =SUMIFS('Cost by Tier'!$K$5:$K$16,'Cost by Tier'!$A$5:$A$16,$A31) -> 34800 | D31: =C31+Questco!$G$6+Questco!$G$7+Questco!$G$8+Questco!$E$18+'401(k)'!$C$37 -> 45686.21 | E31: =SUMIFS('Cost by Tier'!$P$5:$P$16,'Cost by Tier'!$A$5:$A$16,$A31) -> 14196 | F31: =D31+E31+IF('401(k)'!$C$8="Employer",0,'401(k)'!H24) -> 59942.21 | G31: =D31+SUMPRODUCT(('Cost by Tier'!$A$5:$A$16=$A31)*'Cost by Tier'!$O$5:$O$16*'Cost by Tier'!$D$5:$D$16) -> 94882.21
A32: ANG TRAD 2000/4000 | B32: N | C32: =SUMIFS('Cost by Tier'!$K$5:$K$16,'Cost by Tier'!$A$5:$A$16,$A32) -> 34800 | D32: =C32+Questco!$G$6+Questco!$G$7+Questco!$G$8+Questco!$E$18+'401(k)'!$C$37 -> 45686.21 | E32: =SUMIFS('Cost by Tier'!$P$5:$P$16,'Cost by Tier'!$A$5:$A$16,$A32) -> 20119.44 | F32: =D32+E32+IF('401(k)'!$C$8="Employer",0,'401(k)'!H24) -> 65865.65 | G32: =D32+SUMPRODUCT(('Cost by Tier'!$A$5:$A$16=$A32)*'Cost by Tier'!$O$5:$O$16*'Cost by Tier'!$D$5:$D$16) -> 93805.65
A33: ANG TRAD 1000/2000 | B33: N | C33: =SUMIFS('Cost by Tier'!$K$5:$K$16,'Cost by Tier'!$A$5:$A$16,$A33) -> 34800 | D33: =C33+Questco!$G$6+Questco!$G$7+Questco!$G$8+Questco!$E$18+'401(k)'!$C$37 -> 45686.21 | E33: =SUMIFS('Cost by Tier'!$P$5:$P$16,'Cost by Tier'!$A$5:$A$16,$A33) -> 26170.08 | F33: =D33+E33+IF('401(k)'!$C$8="Employer",0,'401(k)'!H24) -> 71916.29 | G33: =D33+SUMPRODUCT(('Cost by Tier'!$A$5:$A$16=$A33)*'Cost by Tier'!$O$5:$O$16*'Cost by Tier'!$D$5:$D$16) -> 85856.29
A35: Onyx's medical column is the same across all three plans because the contribution is a fixed dollar amount and Angle's minimum funding never binds at these settings. A richer plan costs Onyx nothing extra and costs the employee the whole difference. Lower the contribution far enough on the Contributions tab and the minimum starts to bind - the check column there says so.
A36: Angle offers no dental or vision. Questco quotes both as employee-paid, so neither appears in Onyx's cost here.
